application/__init__.py
application/app.py
database/__init__.py
database/firebase.py
2023_assignment1_viewscounter-0.0.8.dist-info/LICENSE
2023_assignment1_viewscounter-0.0.8.dist-info/METADATA
2023_assignment1_viewscounter-0.0.8.dist-info/WHEEL
2023_assignment1_viewscounter-0.0.8.dist-info/top_level.txt
2023_assignment1_viewscounter-0.0.8.dist-info/RECORD
